zwoasi/__init__.py
zwoasi-0.1.0.1.dist-info/AUTHORS.rst
zwoasi-0.1.0.1.dist-info/LICENSE
zwoasi-0.1.0.1.dist-info/METADATA
zwoasi-0.1.0.1.dist-info/WHEEL
zwoasi-0.1.0.1.dist-info/top_level.txt
zwoasi-0.1.0.1.dist-info/RECORD
