Metadata-Version: 2.1
Name: zwoasi
Version: 0.1.0.1
Summary: Python binding for the ZWO ASI v2 library.
Home-page: https://github.com/stevemarple/python-zwoasi
Author: Steve Marple
Author-email: s.marple@lancaster.ac.uk
License: MIT
Platform: UNKNOWN
Classifier: Development Status :: 4 - Beta
Classifier: Intended Audience :: Education
Classifier: Intended Audience :: Science/Research
Classifier: Natural Language :: English
Classifier: License :: OSI Approved :: MIT License
Classifier: Operating System :: OS Independent
Classifier: Programming Language :: Python
Classifier: Programming Language :: Python :: 2
Classifier: Programming Language :: Python :: 2.7
Classifier: Programming Language :: Python :: 3
Classifier: Programming Language :: Python :: 3.3
Classifier: Topic :: Software Development :: Libraries :: Python Modules
License-File: LICENSE
License-File: AUTHORS.rst
Requires-Dist: numpy (>=1.7)
Requires-Dist: six
